libcodebusters/Decrypt.py
libcodebusters/Encrypt.py
libcodebusters/Utils.py
libcodebusters/__init__.py
libcodebusters-1.1.0.dist-info/LICENSE
libcodebusters-1.1.0.dist-info/METADATA
libcodebusters-1.1.0.dist-info/WHEEL
libcodebusters-1.1.0.dist-info/top_level.txt
libcodebusters-1.1.0.dist-info/RECORD
