Metadata-Version: 2.1
Name: libcodebusters
Version: 1.1.0
Summary: Encoding and decoding various ciphers in Python
Home-page: https://github.com/smayya337/libcodebusters
Author: Shreyas Mayya
Author-email: smayya337@gmail.com
License: UNKNOWN
Platform: UNKNOWN
Classifier: Programming Language :: Python :: 3
Classifier: License :: OSI Approved :: MIT License
Classifier: Operating System :: OS Independent
Requires-Python: >=3.6
Requires-Dist: numpy
Requires-Dist: sympy
